{
  "Beijing Language and Culture University（北京语言文化大学）|北京": "beijing-language-and-culture-university",
  "Peking University Chinese Language Program（北京大学中文语言学校）|北京": "peking-university-chinese-language-program",
  "Beijing Normal University（北京师范大学汉语言文化学院）|北京": "beijing-normal-university",
  "Mandarin House 漫德林（漫德林教育）|北京": "mandarin-house",
  "LTL Language School（LTL中文学校）|北京": "ltl-language-schoolltl",
  "Mandarin Zone School（普通话学校）|北京": "mandarin-zone-school",
  "That's Mandarin（普通话学校）|北京": "thats-mandarin",
  "Hutong School (Now That's Mandarin)（胡同学校）|北京": "hutong-school-now-thats-mandarin",
  "Tsinghua University（清华大学）|北京": "tsinghua-university",
  "Fudan University（复旦大学国际文化交流学院）|上海": "fudan-university",
  "Shanghai Jiao Tong University (SJTU)（上海交通大学汉语进修项目）|上海": "shanghai-jiao-tong-university-sjtu",
  "Tongji University（同济大学国际学院）|上海": "tongji-university",
  "East China Normal University (ECNU)（华东师范大学）|上海": "east-china-normal-university-ecnu",
  "Shanghai International Studies University (SISU)（上海外国语大学）|上海": "shanghai-international-studies-university-sisu",
  "Mandarin House（漫德林教育）|上海": "mandarin-house-2",
  "LTL Shanghai（LTL中文学校上海）|上海": "ltl-shanghailtl",
  "SN Mandarin（南北中文学校）|上海": "sn-mandarin",
  "MEIZHI Mandarin School（美兹中文学校）|上海": "meizhi-mandarin-school",
  "iMandarin Language School（爱玛达中文学校）|上海": "imandarin-language-school",
  "Silk Mandarin（锦绣中文学校）|上海": "silk-mandarin",
  "That's Mandarin Shanghai（普通话学校上海）|上海": "thats-mandarin-shanghai",
  "Hanbridge Mandarin（汉桥汉语学校）|深圳": "hanbridge-mandarin",
  "XMandarin Chinese Language School（心文中文学校）|深圳": "xmandarin-chinese-language-school",
  "Sichuan University（四川大学）|成都": "sichuan-university",
  "That's Mandarin Chengdu（普通话学校成都）|成都": "thats-mandarin-chengdu",
  "XMandarin Chengdu（心文中文学校成都）|成都": "xmandarin-chengdu",
  "Hanbridge Mandarin Chengdu（汉桥汉语学校成都）|成都": "hanbridge-mandarin-chengdu",
  "Mandarin House Chengdu（漫德林教育成都）|成都": "mandarin-house-chengdu",
  "Zhejiang University（浙江大学国际学院）|杭州": "zhejiang-university",
  "Hangzhou Normal University（杭州师范大学国教院）|杭州": "hangzhou-normal-university",
  "Hangzhou Dianzi University（杭州电子科技大学）|杭州": "hangzhou-dianzi-university",
  "XMandarin Hangzhou（心文中文学校杭州）|杭州": "xmandarin-hangzhou",
  "That's Mandarin Hangzhou（普通话学校杭州）|杭州": "thats-mandarin-hangzhou",
  "Nanjing University（南京大学）|南京": "nanjing-university",
  "Silk Mandarin Suzhou（锦绣中文学校苏州）|蘇州": "silk-mandarin-suzhou",
  "That's Mandarin Suzhou（普通话学校苏州）|蘇州": "thats-mandarin-suzhou",
  "Mandarin House Suzhou（漫德林教育苏州）|蘇州": "mandarin-house-suzhou",
  "CLI Chinese Language Institute（中文学院）|桂林": "cli-chinese-language-institute",
  "Omeida Chinese Academy（欧美达中文学院）|桂林": "omeida-chinese-academy",
  "Keats School（凯特学校）|昆明": "keats-school",
  "Xiamen University（厦门大学汉语国际教育学院）|廈門": "xiamen-university",
  "Jinan University（暨南大学华夏文化学院）|廣州": "jinan-university",
  "Mandarin House Guangzhou（漫德林教育广州）|廣州": "mandarin-house-guangzhou",
  "iMandarin Guangzhou（爱玛达中文学校广州）|廣州": "imandarin-guangzhou",
  "New Concept Mandarin（新概念汉语学校）|廣州": "new-concept-mandarin",
  "Keats School Guangzhou（凯特学校广州）|廣州": "keats-school-guangzhou",
  "Xi'an Jiaotong University（西安交通大学国际教育学院）|西安": "xian-jiaotong-university",
  "Wuhan University（武汉大学国际教育学院）|武漢": "wuhan-university",
  "Wuhan University of Technology（武汉理工大学国际学生中心）|武漢": "wuhan-university-of-technology",
  "Mandarin Garden Wuhan（汉语花园武汉）|武漢": "mandarin-garden-wuhan",
  "Peking University Chinese Language Program（北京大学中文学校西安）|西安": "peking-university-chinese-language-program-2",
  "Tianjin University（天津大学国际学校）|天津": "tianjin-university",
  "Tianjin Foreign Studies University（天津外国语大学）|天津": "tianjin-foreign-studies-university",
  "Chongqing University（重庆大学）|重慶": "chongqing-university",
  "Hutong School (That's Mandarin) Chongqing（胡同学校重庆）|重慶": "hutong-school-thats-mandarin-chongqing",
  "Dalian University of Foreign Languages（大连外国语大学）|大連": "dalian-university-of-foreign-languages",
  "Dalian Smile Chinese（微笑汉语学校大连）|大連": "dalian-smile-chinese",
  "Harbin Institute of Technology（哈尔滨工业大学）|哈爾浜": "harbin-institute-of-technology",
  "XMandarin Qingdao（心文中文学校青岛）|青島": "xmandarin-qingdao",
  "Hutong School (That's Mandarin) Qingdao（胡同学校青岛）|青島": "hutong-school-thats-mandarin-qingdao",
  "Silk Mandarin Camps Qingdao（锦绣中文学校青岛）|青島": "silk-mandarin-camps-qingdao",
  "Haikou Premier Language School（海口首选语言学校）|海口": "haikou-premier-language-school",
  "Hainan Mandarin Academy（海南普通话学院）|海口": "hainan-mandarin-academy",
  "International School of Sanya（三亚国际学校）|三亞": "international-school-of-sanya",
  "iMandarin Beijing（爱玛达中文学校北京）|北京": "imandarin-beijing",
  "New Concept Mandarin Beijing（新概念汉语学校北京）|北京": "new-concept-mandarin-beijing",
  "iMandarin Chengdu（爱玛达中文学校成都）|成都": "imandarin-chengdu",
  "Silk Mandarin Immersive Camps（锦绣中文学校夏令营）|Multiple Cities": "silk-mandarin-immersive-camps-multiple-cities",
  "Hutong School (That's Mandarin) Hangzhou（胡同学校杭州）|杭州": "hutong-school-thats-mandarin-hangzhou",
  "Hutong School (That's Mandarin) Shanghai（胡同学校上海）|上海": "hutong-school-thats-mandarin-shanghai",
  "Hutong School (That's Mandarin) Suzhou（胡同学校苏州）|蘇州": "hutong-school-thats-mandarin-suzhou",
  "LTL Beihai（LTL中文学校北海）|北海": "ltl-beihailtl",
  "LTL Xi'an（LTL中文学校西安）|西安": "ltl-xianltl",
  "LTL Chengde（LTL中文学校承德）|承德": "ltl-chengdeltl",
  "New Concept Mandarin Shenzhen（新概念汉语学校深圳）|深圳": "new-concept-mandarin-shenzhen",
  "New Concept Mandarin Suzhou（新概念汉语学校苏州）|蘇州": "new-concept-mandarin-suzhou",
  "New Concept Mandarin Nanjing（新概念汉语学校南京）|南京": "new-concept-mandarin-nanjing",
  "New Concept Mandarin Shanghai（新概念汉语学校上海）|上海": "new-concept-mandarin-shanghai",
  "New Concept Mandarin Dongguan（新概念汉语学校东莞）|東莞": "new-concept-mandarin-dongguan",
  "iMandarin Qingdao（爱玛达中文学校青岛）|青島": "imandarin-qingdao",
  "Mandarin House Hong Kong（漫德林教育香港）|香港": "mandarin-house-hong-kong",
  "Zhongshan University（中山大学）|廣州": "zhongshan-university",
  "Sun Yat-sen University（孙中山大学）|廣州": "sun-yat-sen-university",
  "Huazhong University of Science and Technology（华中科技大学）|武漢": "huazhong-university-of-science-and-technology",
  "Nanjing University of Information Science and Technology（南京信息工程大学）|南京": "nanjing-university-of-information-science-and-tech",
  "Nanjing University of Aeronautics and Astronautics（南京航空航天大学）|南京": "nanjing-university-of-aeronautics-and-astronautics",
  "Nanjing Forestry University（南京林业大学）|南京": "nanjing-forestry-university",
  "Zhejiang Shuren University（浙江树人大学）|杭州": "zhejiang-shuren-university",
  "Zhejiang University of Science and Technology（浙江科技学院）|杭州": "zhejiang-university-of-science-and-technology",
  "Zhejiang University of Finance and Economics（浙江财经大学）|杭州": "zhejiang-university-of-finance-and-economics",
  "Tianjin University of Traditional Chinese Medicine（天津中医药大学）|天津": "tianjin-university-of-traditional-chinese-medicine",
  "Beijing Foreign Studies University（北京外国语大学）|北京": "beijing-foreign-studies-university",
  "Meizhi Mandarin Xujiahui（美兹中文学校徐汇）|上海": "meizhi-mandarin-xujiahui",
  "Meizhi Mandarin Hongqiao-Gubei（美兹中文学校虹桥）|上海": "meizhi-mandarin-hongqiao-gubei",
  "National Taiwan University - International Chinese Language Program (ICLP)|台北": "national-taiwan-university-international-chinese-l",
  "National Taiwan University - Chinese Language Division (CLD)|台北": "national-taiwan-university-chinese-language-divisi",
  "National Taiwan Normal University - Mandarin Training Center (MTC)|台北": "national-taiwan-normal-university-mandarin-trainin",
  "Taipei Language Institute (TLI)|台北": "taipei-language-institute-tli",
  "Tamkang University - Chinese Language Center|台北": "tamkang-university-chinese-language-center",
  "Shih Chien University - Chinese Language Center|台北": "shih-chien-university-chinese-language-center",
  "National Chengchi University - Chinese Language Center|台北": "national-chengchi-university-chinese-language-cent",
  "Fu Jen Catholic University - Center of Chinese Language and Culture|台北": "fu-jen-catholic-university-center-of-chinese-langu",
  "National Yang Ming Chiao Tung University - Chinese Language Center|新竹": "national-yang-ming-chiao-tung-university-chinese-l",
  "National Sun Yat-sen University - Chinese Language Center|高雄": "national-sun-yat-sen-university-chinese-language-c",
  "Wenzao Ursuline University of Languages - Chinese Language Center|高雄": "wenzao-ursuline-university-of-languages-chinese-la",
  "National Chung Hsing University - Chinese Language Center|台中": "national-chung-hsing-university-chinese-language-c",
  "National Taichung University of Education - Chinese Language Center|台中": "national-taichung-university-of-education-chinese-",
  "National Kaohsiung Normal University - Center of Language and Culture Teaching|高雄": "national-kaohsiung-normal-university-center-of-lan",
  "Taiwan Mandarin Institute (TMI)|台北": "taiwan-mandarin-institute-tmi",
  "Learning the Language (LTL) - Taiwan|台北": "learning-the-language-ltl-taiwan",
  "Taiwan Chinese Academy (TCA)|台北": "taiwan-chinese-academy-tca",
  "Taiwan Center for Mandarin Learning (TCML)|台北": "taiwan-center-for-mandarin-learning-tcml",
  "ShuoHao Language Center|台北": "shuohao-language-center",
  "Taipei Mandarin Center (TMC)|台北": "taipei-mandarin-center-tmc",
  "Oh Young Language Center|台中": "oh-young-language-center",
  "Lingo Lab Mandarin Institute|台北": "lingo-lab-mandarin-institute",
  "National Mandarin Institute|台北": "national-mandarin-institute",
  "Taiwan Intensive Summer and Semester Language Program (TISLP)|Multiple cities": "taiwan-intensive-summer-and-semester-language-prog",
  "Mandarin Channel School|香港": "mandarin-channel-school",
  "Hong Kong Language Learning Centre (HKLLC)|香港": "hong-kong-language-learning-centre-hkllc",
  "Hong Kong Language School|香港": "hong-kong-language-school",
  "University of Hong Kong - Chinese Language Centre|香港": "university-of-hong-kong-chinese-language-centre",
  "New Concept Mandarin|香港": "new-concept-mandarin-2",
  "New Concept Cantonese|香港": "new-concept-cantonese",
  "Hong Kong Institute of Languages|香港": "hong-kong-institute-of-languages",
  "Mandarin Time School|香港": "mandarin-time-school",
  "Chinese International School|香港": "chinese-international-school",
  "Sogang University - Korean Language Education Center (KLEC)|ソウル": "sogang-university-korean-language-education-center",
  "Yonsei University - Korean Language Institute (KLI)|ソウル": "yonsei-university-korean-language-institute-kli",
  "Seoul National University - Korean Language & Culture Program (KLCP)|ソウル": "seoul-national-university-korean-language-culture-",
  "Konkuk University - Korean Language Institute (KLI)|ソウル": "konkuk-university-korean-language-institute-kli",
  "Hongik University - International Language Institute|ソウル": "hongik-university-international-language-institute",
  "Kyunghee University - Institute of International Education|ソウル": "kyunghee-university-institute-of-international-edu",
  "LEXIS KOREA|ソウル": "lexis-korea",
  "KLIFF (Korean Language Institute For Foreigners)|ソウル": "kliff-korean-language-institute-for-foreigners",
  "Korean Language Institute For Foreigners (Pusan)|釜山": "korean-language-institute-for-foreigners-pusan",
  "Kyungsung Language Center (KLC)|釜山": "kyungsung-language-center-klc",
  "Silla Korean Language Institute (Silla KLI)|ソウル": "silla-korean-language-institute-silla-kli",
  "Green Korean Language School (GKLS)|ソウル": "green-korean-language-school-gkls",
  "EWHA Womans University - Ewha Language Center|ソウル": "ewha-womans-university-ewha-language-center",
  "Chung-Ang University - Korean Language Institute|ソウル": "chung-ang-university-korean-language-institute",
  "Go! Go! Hanguk - Korean Language School Network|ソウル": "go-go-hanguk-korean-language-school-network",
  "Genki Japanese and Culture School|東京": "genki-japanese-and-culture-school",
  "Genki Japanese and Culture School - Tokyo|東京": "genki-japanese-and-culture-school-tokyo",
  "Genki Japanese and Culture School - Fukuoka|福岡": "genki-japanese-and-culture-school-fukuoka",
  "JaLS GROUP (Japanese Language School)|東京": "jals-group-japanese-language-school",
  "JaLS GROUP - Kyoto|京都": "jals-group-kyoto",
  "ISI Japanese Language School|東京": "isi-japanese-language-school",
  "KCP International Japanese Language School|東京": "kcp-international-japanese-language-school",
  "Coto Academy|東京": "coto-academy",
  "Nihongo Center|京都": "nihongo-center",
  "Kyoto Japanese Language School (KJLS)|京都": "kyoto-japanese-language-school-kjls",
  "Human Academy Japanese Language School|東京": "human-academy-japanese-language-school",
  "Human Academy Japanese Language School - Osaka|大阪": "human-academy-japanese-language-school-osaka",
  "KAI Japanese Language School|東京": "kai-japanese-language-school",
  "JCLI Japanese Language School|東京": "jcli-japanese-language-school",
  "YMCA Tokyo Japanese Language School|東京": "ymca-tokyo-japanese-language-school",
  "Osaka YMCA International College|大阪": "osaka-ymca-international-college",
  "Meiji Academy|札幌": "meiji-academy",
  "ARC Academy|東京": "arc-academy",
  "TSL Chiang Mai (Thai as a Second Language)|チェンマイ": "tsl-chiang-mai-thai-as-a-second-language",
  "Pro Language School|バンコク": "pro-language-school",
  "Payap University - Intensive Thai Program|チェンマイ": "payap-university-intensive-thai-program",
  "Lanna Language School|チェンマイ": "lanna-language-school",
  "American University Alumni (AUA)|チェンマイ": "american-university-alumni-aua",
  "AAA Thai Language School Bangkok|バンコク": "aaa-thai-language-school-bangkok",
  "ALA Language School Bangkok|バンコク": "ala-language-school-bangkok",
  "Thai Language Center - Bangkok (Multiple Options)|バンコク": "thai-language-center-bangkok-multiple-options",
  "GEOS Thailand (Thai Language Programs)|バンコク": "geos-thailand-thai-language-programs",
  "Thai Language Schools - Nationwide Network|バンコク": "thai-language-schools-nationwide-network",
  "Cairns College of English & Business (CCEB)|ケアンズ": "cairns-college-of-english-business-cceb",
  "Tasmanian College of English (TCE)|ホバート": "tasmanian-college-of-english-tce",
  "University of Tasmania English Language Centre|ホバート": "university-of-tasmania-english-language-centre",
  "Hobart Language Centre (VLLC)|ホバート": "hobart-language-centre-vllc",
  "ILSC Language Schools Adelaide|アデレード": "ilsc-language-schools-adelaide",
  "English College of Adelaide (ECA)|アデレード": "english-college-of-adelaide-eca",
  "Impact English College|Sunshine Coast": "impact-english-college-sunshine-coast",
  "Lexis English Melbourne|メルボルン": "lexis-english-melbourne",
  "LSI Brisbane|ブリスベン": "lsi-brisbane",
  "Express English College|マンチェスター": "express-english-college",
  "Britannia English School|マンチェスター": "britannia-english-school",
  "MC Academy Manchester|マンチェスター": "mc-academy-manchester",
  "EC Manchester|マンチェスター": "ec-manchester",
  "Essential English Centre|マンチェスター": "essential-english-centre",
  "Kaplan International Manchester|マンチェスター": "kaplan-international-manchester",
  "LILA*|リバプール": "lila",
  "New College Group Liverpool|リバプール": "new-college-group-liverpool",
  "HIL Liverpool|リバプール": "hil-liverpool",
  "Centre of English Studies (CES) Leeds|リーズ": "centre-of-english-studies-ces-leeds",
  "Leeds Language College|リーズ": "leeds-language-college",
  "Yorkshire College|リーズ": "yorkshire-college",
  "English Path (EP) Leeds|リーズ": "english-path-ep-leeds",
  "Anglo-Continental|ボーンマス": "anglo-continental",
  "Cavendish School of English|ボーンマス": "cavendish-school-of-english",
  "Europa School of English|ボーンマス": "europa-school-of-english",
  "The Bournemouth School of English|ボーンマス": "the-bournemouth-school-of-english",
  "Bayswater Bournemouth|ボーンマス": "bayswater-bournemouth",
  "Twin English Centre Eastbourne|イーストボーン": "twin-english-centre-eastbourne",
  "St Giles International Eastbourne|イーストボーン": "st-giles-international-eastbourne",
  "Kaplan International Torquay|トーキー": "kaplan-international-torquay",
  "Torquay International School|トーキー": "torquay-international-school",
  "Glasgow School of English|グラスゴー": "glasgow-school-of-english",
  "The Horner School of English|ダブリン": "the-horner-school-of-english",
  "Irish College of English|ダブリン": "irish-college-of-english",
  "ISI Dublin|ダブリン": "isi-dublin",
  "International House Dublin|ダブリン": "international-house-dublin",
  "Erin College Dublin|ダブリン": "erin-college-dublin",
  "ELI Schools Dublin|ダブリン": "eli-schools-dublin",
  "Centre of English Studies (CES) Cork|コーク": "centre-of-english-studies-ces-cork",
  "Erin College Cork|コーク": "erin-college-cork",
  "GCI (Galway Cultural Institute)|ゴールウェイ": "gci-galway-cultural-institute",
  "University of Galway English Language Centre|ゴールウェイ": "university-of-galway-english-language-centre",
  "Corrib English|ゴールウェイ": "corrib-english",
  "University of Limerick Language Centre|リムリック": "university-of-limerick-language-centre",
  "Rightword Institute|リムリック": "rightword-institute",
  "Waterford English Language Centres (WELC)|ウォーターフォード": "waterford-english-language-centres-welc",
  "The International School of English Waterford|ウォーターフォード": "the-international-school-of-english-waterford",
  "EFL Ireland|ウォーターフォード": "efl-ireland",
  "English Language Partners Wellington|ウェリントン": "english-language-partners-wellington",
  "Wilkinson's English Language School|クライストチャーチ": "wilkinsons-english-language-school",
  "English Language Partners Christchurch|クライストチャーチ": "english-language-partners-christchurch",
  "NTA English Academy|クライストチャーチ": "nta-english-academy",
  "Waikato Institute of Education|ハミルトン": "waikato-institute-of-education",
  "English Language Partners Hamilton|ハミルトン": "english-language-partners-hamilton",
  "Mount Maunganui Language Centre|Tauranga": "mount-maunganui-language-centre-tauranga",
  "English Language Partners Dunedin|ダニーデン": "english-language-partners-dunedin",
  "LSNZ Dunedin|ダニーデン": "lsnz-dunedin",
  "Alpha School of English Language Malta|Sliema": "alpha-school-of-english-language-malta-sliema",
  "Ascencia Malta|Saint Julian": "ascencia-malta-saint-julian",
  "Good Hope Studies|ケープタウン": "good-hope-studies",
  "Avenue English Language School|ケープタウン": "avenue-english-language-school",
  "Cape Studies|ケープタウン": "cape-studies",
  "Bayswater Cape Town|ケープタウン": "bayswater-cape-town",
  "SSLC Language College Toronto|トロント": "sslc-language-college-toronto",
  "Oxford International Toronto|トロント": "oxford-international-toronto",
  "VGC International College Vancouver|バンクーバー": "vgc-international-college-vancouver",
  "SSLC Language College Vancouver|バンクーバー": "sslc-language-college-vancouver",
  "Global Village Calgary|カルガリー": "global-village-calgary",
  "ANNE'S Language House (ALH)|カルガリー": "annes-language-house-alh",
  "OHC Calgary|カルガリー": "ohc-calgary",
  "Global Village Edmonton|エドモントン": "global-village-edmonton",
  "NorQuest College ESL|エドモントン": "norquest-college-esl",
  "MacEwan University ESL|エドモントン": "macewan-university-esl",
  "Portland English Language Academy (PELA)|ポートランド": "portland-english-language-academy-pela",
  "Pacific International Academy (PIA)|ポートランド": "pacific-international-academy-pia",
  "Columbia School of English|ポートランド": "columbia-school-of-english",
  "Aston International Austin|Austin": "aston-international-austin-austin",
  "CEL San Diego|サンディエゴ": "cel-san-diego",
  "USAELC San Diego|サンディエゴ": "usaelc-san-diego",
  "Boston International Academy|ボストン": "boston-international-academy",
  "ASC English Boston|ボストン": "asc-english-boston",
  "Colorado School of English|デンバー": "colorado-school-of-english",
  "ELS Minneapolis|Minneapolis": "els-minneapolis-minneapolis",
  "CLIC International House|セビリア": "clic-international-house",
  "Don Quijote|グラナダ": "don-quijote",
  "Hispania Schools|マラガ": "hispania-schools",
  "Enforex|Multiple Spanish locations": "enforex-multiple-spanish-locations",
  "ELE USAL Mallorca|Palma de Mallorca": "ele-usal-mallorca-palma-de-mallorca",
  "Camino Barcelona|バルセロナ": "camino-barcelona",
  "Speakeasy BCN|バルセロナ": "speakeasy-bcn",
  "Cervantes Barcelona|バルセロナ": "cervantes-barcelona",
  "Ole Languages|バルセロナ": "ole-languages",
  "BCNLIP|バルセロナ": "bcnlip",
  "Inhispania Madrid|マドリード": "inhispania-madrid",
  "Walk Spanish Madrid|マドリード": "walk-spanish-madrid",
  "Eureka Madrid|マドリード": "eureka-madrid",
  "TILDE Madrid|マドリード": "tilde-madrid",
  "AIL Madrid|マドリード": "ail-madrid",
  "TANDEM Madrid|マドリード": "tandem-madrid",
  "Cervantes Madrid|マドリード": "cervantes-madrid",
  "Spaneasy Learning Madrid|マドリード": "spaneasy-learning-madrid",
  "Spanish Academy Antiguena|セビリア": "spanish-academy-antiguena",
  "Go! Go! España|Multiple Spanish cities": "go-go-espana-multiple-spanish-cities",
  "Language International Spain|Multiple Spanish cities": "language-international-spain-multiple-spanish-citi",
  "Estudia-España|Multiple Spanish cities": "estudia-espana-multiple-spanish-cities",
  "FEDELE|Multiple Spanish cities": "fedele-multiple-spanish-cities",
  "Learning Languages Abroad|Multiple Spanish cities": "learning-languages-abroad-multiple-spanish-cities",
  "LanguageCourse.net Spain|Multiple Spanish cities": "languagecoursenet-spain-multiple-spanish-cities",
  "Goethe-Institut|ベルリン": "goethe-institut",
  "Humboldt-Institut|Multiple German cities": "humboldt-institut-multiple-german-cities",
  "Sprachschule Aktiv|Düsseldorf": "sprachschule-aktiv-dusseldorf",
  "Deutsch Akademie|Multiple German cities": "deutsch-akademie-multiple-german-cities",
  "Euro-Schulen|Bonn": "euro-schulen-bonn",
  "F+U Language School Heidelberg|ハイデルベルク": "fu-language-school-heidelberg",
  "inlingua Cologne|ケルン": "inlingua-cologne",
  "Speakeasy Munich|ミュンヘン": "speakeasy-munich",
  "Did deutsch-institut Munich|ミュンヘン": "did-deutsch-institut-munich",
  "GLS German Courses Berlin|ベルリン": "gls-german-courses-berlin",
  "BWS Germanlingua|Multiple German cities": "bws-germanlingua-multiple-german-cities",
  "Sprachschule.org Directory|Multiple German cities": "sprachschuleorg-directory-multiple-german-cities",
  "Language International Germany|Multiple German cities": "language-international-germany-multiple-german-cit",
  "LanguageCourse.net Germany|Multiple German cities": "languagecoursenet-germany-multiple-german-cities",
  "GoAbroad Germany|Multiple German cities": "goabroad-germany-multiple-german-cities",
  "Fintiba Language Schools|Multiple German cities": "fintiba-language-schools-multiple-german-cities",
  "Dream Studies Abroad|Multiple German cities": "dream-studies-abroad-multiple-german-cities",
  "OneWorld365|Multiple German cities": "oneworld365-multiple-german-cities",
  "ESL Language Schools Germany|Multiple German cities": "esl-language-schools-germany-multiple-german-citie",
  "LanguageInt Germany|Multiple German cities": "languageint-germany-multiple-german-cities",
  "Sprachlehrer Aktiv|Multiple German cities": "sprachlehrer-aktiv-multiple-german-cities",
  "Sprachschule Aktiv München|Multiple German cities": "sprachschule-aktiv-munchen-multiple-german-cities",
  "Go Abroad Germany|Multiple German cities": "go-abroad-germany-multiple-german-cities",
  "Alliance Française de France|マルセイユ": "alliance-francaise-de-france",
  "Les Ateliers FL|パリ": "les-ateliers-fl",
  "IS Aix-en-Provence|Aix-en-Provence": "is-aix-en-provence-aix-en-provence",
  "Millefeuille Provence|Near Avignon": "millefeuille-provence-near-avignon",
  "Institut de Langue et de Culture Françaises (ILCF)|リヨン": "institut-de-langue-et-de-culture-francaises-ilcf",
  "Kaplan International France|リヨン": "kaplan-international-france",
  "Alpadia Language Schools|Multiple French cities": "alpadia-language-schools-multiple-french-cities",
  "NACEL Language Schools|Multiple French cities": "nacel-language-schools-multiple-french-cities",
  "French-Paris|パリ": "french-paris",
  "Go! Go! France|Multiple French cities": "go-go-france-multiple-french-cities",
  "Language International France|Multiple French cities": "language-international-france-multiple-french-citi",
  "FLE.fr Directory|Multiple French cities": "flefr-directory-multiple-french-cities",
  "LanguageCourse.net France|Multiple French cities": "languagecoursenet-france-multiple-french-cities",
  "CIA France|Multiple French cities": "cia-france-multiple-french-cities",
  "UCLy Lyon|リヨン": "ucly-lyon",
  "ESL Language Schools France|Multiple French cities": "esl-language-schools-france-multiple-french-cities",
  "EF French School France|Multiple French cities": "ef-french-school-france-multiple-french-cities",
  "Apple Languages France|Multiple French cities": "apple-languages-france-multiple-french-cities",
  "Go Overseas French Schools|Multiple French cities": "go-overseas-french-schools-multiple-french-cities",
  "GoAbroad French Schools|Multiple French cities": "goabroad-french-schools-multiple-french-cities",
  "Dream Studies Abroad France|Multiple French cities": "dream-studies-abroad-france-multiple-french-cities",
  "ASILS - Association of Italian Language Schools|Turin": "asils-association-of-italian-language-schools-turi",
  "Cultura Italiana Bologna|ボローニャ": "cultura-italiana-bologna",
  "Madrelingua Italian Language School Bologna|ボローニャ": "madrelingua-italian-language-school-bologna",
  "ARCA Bologna|ボローニャ": "arca-bologna",
  "ALCE - Accademia Lingue e Culture Europee|ボローニャ": "alce-accademia-lingue-e-culture-europee",
  "Lucca Italian School|Lucca": "lucca-italian-school-lucca",
  "Fondazione Campus Lucca|Lucca": "fondazione-campus-lucca-lucca",
  "Centro Koinè|Lucca": "centro-koine-lucca",
  "Dante Alighieri Palermo|Palermo": "dante-alighieri-palermo-palermo",
  "Scuola Italiano Sicilia|Palermo": "scuola-italiano-sicilia-palermo",
  "Culturforum Sicilia|Palermo": "culturforum-sicilia-palermo",
  "International House Palermo|Palermo": "international-house-palermo-palermo",
  "One World Italiano School|Cagliari": "one-world-italiano-school-cagliari",
  "Scuola Leonardo da Vinci|フィレンツェ": "scuola-leonardo-da-vinci",
  "Institute Galilei Florence|フィレンツェ": "institute-galilei-florence",
  "Michelangelo School Florence|フィレンツェ": "michelangelo-school-florence",
  "NACEL Italy|ローマ": "nacel-italy",
  "LanguageCourse.net Italy|Multiple Italian cities": "languagecoursenet-italy-multiple-italian-cities",
  "Lusa Language School|リスボン": "lusa-language-school",
  "Português et Cetera|リスボン": "portugues-et-cetera",
  "CIAL|リスボン": "cial",
  "Portuguese Connection|リスボン": "portuguese-connection",
  "Iberlínguas|リスボン": "iberlinguas",
  "Learn Portuguese in Lisbon|リスボン": "learn-portuguese-in-lisbon",
  "NIALP|リスボン": "nialp",
  "UvA Talen|アムステルダム": "uva-talen",
  "Taalhuis Amsterdam|アムステルダム": "taalhuis-amsterdam",
  "NedLes|アムステルダム": "nedles",
  "Volksuniversiteit Amsterdam|アムステルダム": "volksuniversiteit-amsterdam",
  "Direct Dutch|The Hague": "direct-dutch-the-hague",
  "ActiLingua Academy|ウィーン": "actilingua-academy",
  "INNES Vienna|ウィーン": "innes-vienna",
  "University of Vienna Language Center|ウィーン": "university-of-vienna-language-center",
  "ESL Austria|ウィーン": "esl-austria",
  "Language International Austria|ウィーン": "language-international-austria",
  "Alemania|チューリッヒ": "alemania",
  "ILS Zürich|チューリッヒ": "ils-zurich",
  "LSI Switzerland|チューリッヒ": "lsi-switzerland",
  "Kaplan International Switzerland|Montreux": "kaplan-international-switzerland-montreux",
  "ETH Zurich Language Center|チューリッヒ": "eth-zurich-language-center",
  "Alexander the Great School|アテネ": "alexander-the-great-school",
  "The Athens Centre|アテネ": "the-athens-centre",
  "Modern Greek Language Teaching Centre (University of Athens)|アテネ": "modern-greek-language-teaching-centre-university-o",
  "School of Modern Greek Language (Aristotle University)|Thessaloniki": "school-of-modern-greek-language-aristotle-universi",
  "Hellenic-American Union|アテネ": "hellenic-american-union",
  "Centre for the Greek Language (Thessaloniki)|Thessaloniki": "centre-for-the-greek-language-thessaloniki-thessal",
  "Charles University ÚJOP|プラハ": "charles-university-ujop",
  "Czech Courses|プラハ": "czech-courses",
  "Czech Language Training|プラハ": "czech-language-training",
  "Integration Centre Prague|プラハ": "integration-centre-prague",
  "Taan Spanish School|プラヤ・デル・カルメン": "taan-spanish-school",
  "Alegre Spanish Schools|プラヤ・デル・カルメン": "alegre-spanish-schools",
  "Spanish Center Merida|Mérida": "spanish-center-merida-merida",
  "La Casita Spanish School|Mérida": "la-casita-spanish-school-merida",
  "IH Oaxaca|オアハカ": "ih-oaxaca",
  "Linguaschools Guanajuato|Guanajuato": "linguaschools-guanajuato-guanajuato",
  "Plateros Spanish Language School|Guanajuato": "plateros-spanish-language-school-guanajuato",
  "Don Quijote Guanajuato|Guanajuato": "don-quijote-guanajuato-guanajuato",
  "La Hacienda Spanish School|Guanajuato": "la-hacienda-spanish-school-guanajuato",
  "Escuela Falcon Guanajuato|Guanajuato": "escuela-falcon-guanajuato-guanajuato",
  "Spanish Experience Center|Guanajuato": "spanish-experience-center-guanajuato",
  "Instituto Jovel|San Cristóbal": "instituto-jovel-san-cristobal",
  "SanCris Language School|San Cristóbal": "sancris-language-school-san-cristobal",
  "Spanish School Mexico Directory|Multiple Mexican cities": "spanish-school-mexico-directory-multiple-mexican-c",
  "Language International Mexico|Multiple Mexican cities": "language-international-mexico-multiple-mexican-cit",
  "Toucan Spanish|メデジン": "toucan-spanish",
  "Centro Catalina|カルタヘナ": "centro-catalina",
  "Total Spanish|メデジン": "total-spanish",
  "Valley Spanish School|メデジン": "valley-spanish-school",
  "Vamos Academy|ボゴタ": "vamos-academy",
  "Study Spanish Colombia|ボゴタ": "study-spanish-colombia",
  "Universidad de Cartagena|カルタヘナ": "universidad-de-cartagena",
  "National University Colombia|ボゴタ": "national-university-colombia",
  "Los Andes University|ボゴタ": "los-andes-university",
  "Colombian Spanish Directory|Multiple Colombian cities": "colombian-spanish-directory-multiple-colombian-cit",
  "Verbum|ブエノスアイレス": "verbum",
  "Spanish Courses Buenos Aires|ブエノスアイレス": "spanish-courses-buenos-aires",
  "Enforex Argentina|ブエノスアイレス": "enforex-argentina",
  "Spanish School Argentina|ブエノスアイレス": "spanish-school-argentina",
  "Universidad Nacional de Córdoba|Córdoba": "universidad-nacional-de-cordoba-cordoba",
  "Go Overseas Argentina|Multiple Argentine cities": "go-overseas-argentina-multiple-argentine-cities",
  "Language International Argentina|Multiple Argentine cities": "language-international-argentina-multiple-argentin",
  "GoAbroad Argentina|Multiple Argentine cities": "goabroad-argentina-multiple-argentine-cities",
  "LanguageCourse.net Argentina|Multiple Argentine cities": "languagecoursenet-argentina-multiple-argentine-cit",
  "Intercultura Spanish School|Sámara Beach": "intercultura-spanish-school-samara-beach",
  "CPI - Centro Panamericano de Idiomas|Heredia": "cpi-centro-panamericano-de-idiomas-heredia",
  "Tico Lingo Spanish School|Multiple Costa Rican locations": "tico-lingo-spanish-school-multiple-costa-rican-loc",
  "EF Costa Rica|Playa Tamarindo": "ef-costa-rica-playa-tamarindo",
  "Maximo Nivel Costa Rica|San Jose": "maximo-nivel-costa-rica-san-jose",
  "Nosara Spanish Institute|Nosara": "nosara-spanish-institute-nosara",
  "Spanish and More|Multiple Costa Rican locations": "spanish-and-more-multiple-costa-rican-locations",
  "Language International Costa Rica|Multiple Costa Rican locations": "language-international-costa-rica-multiple-costa-r",
  "AMAUTA Spanish School|クスコ": "amauta-spanish-school",
  "Mundo Antiguo Spanish School|クスコ": "mundo-antiguo-spanish-school",
  "Maximo Nivel Peru|クスコ": "maximo-nivel-peru",
  "Wiracocha Spanish School|クスコ": "wiracocha-spanish-school",
  "Peru Spanish|リマ": "peru-spanish",
  "Go Overseas Peru|Multiple Peruvian cities": "go-overseas-peru-multiple-peruvian-cities",
  "Language International Peru|Multiple Peruvian cities": "language-international-peru-multiple-peruvian-citi",
  "Apple Languages Peru|Multiple Peruvian cities": "apple-languages-peru-multiple-peruvian-cities",
  "Aventuras Languages|キト": "aventuras-languages",
  "Yanapuma Spanish School|キト": "yanapuma-spanish-school",
  "AGS Andean Global Studies|Multiple Ecuadorian cities": "ags-andean-global-studies-multiple-ecuadorian-citi",
  "Estudio Sampere Cuenca|クエンカ": "estudio-sampere-cuenca",
  "Instituto Superior de Español|Multiple Ecuadorian cities": "instituto-superior-de-espanol-multiple-ecuadorian-",
  "Ailola Quito|キト": "ailola-quito",
  "Language International Ecuador|Multiple Ecuadorian cities": "language-international-ecuador-multiple-ecuadorian",
  "Go Overseas Ecuador|Multiple Ecuadorian cities": "go-overseas-ecuador-multiple-ecuadorian-cities",
  "Escuela Bellavista|サンティアゴ": "escuela-bellavista",
  "Tandem Santiago|サンティアゴ": "tandem-santiago",
  "Linguaschools Santiago|サンティアゴ": "linguaschools-santiago",
  "Natalislang|サンティアゴ": "natalislang",
  "Interactive Spanish Valparaiso|Valparaíso": "interactive-spanish-valparaiso-valparaiso",
  "Ecela Viña del Mar|Viña del Mar": "ecela-vina-del-mar-vina-del-mar",
  "Ixchel School|アンティグア": "ixchel-school",
  "Spanish Academy Ciudad Vieja|アンティグア": "spanish-academy-ciudad-vieja",
  "InterContinental Spanish Academy|アンティグア": "intercontinental-spanish-academy",
  "Celas Maya|Multiple Guatemalan locations": "celas-maya-multiple-guatemalan-locations",
  "Rio & Learn|リオデジャネイロ": "rio-learn",
  "Caminhos Language Centre|リオデジャネイロ": "caminhos-language-centre",
  "ILC Brasil|リオデジャネイロ": "ilc-brasil",
  "Fast Forward Language Institute|São Paulo": "fast-forward-language-institute-sao-paulo",
  "Fala Aí|リオデジャネイロ": "fala-ai",
  "Estudio Sampere Havana|ハバナ": "estudio-sampere-havana",
  "Barclay Languages|ハバナ": "barclay-languages",
  "Apple Language Courses Cuba|ハバナ": "apple-language-courses-cuba",
  "Sprachcaffe Cuba|ハバナ": "sprachcaffe-cuba",
  "Estudio Hispánico Havana|ハバナ": "estudio-hispanico-havana",
  "English College of Adelaide|アデレード": "english-college-of-adelaide",
  "Academy of English|アデレード": "academy-of-english",
  "SACE - South Australian College of English|アデレード": "sace-south-australian-college-of-english",
  "Curtin English|パース": "curtin-english",
  "TAFE International Western Australia|パース": "tafe-international-western-australia",
  "Cairns Language Centre|ケアンズ": "cairns-language-centre",
  "University of Newcastle English Language Centre|ニューカッスル": "university-of-newcastle-english-language-centre",
  "University of Wollongong English Language Centre|ウーロンゴン": "university-of-wollongong-english-language-centre",
  "Canberra Institute of Technology (CIT)|キャンベラ": "canberra-institute-of-technology-cit",
  "University of Canberra College|キャンベラ": "university-of-canberra-college",
  "Unity College Australia|キャンベラ": "unity-college-australia",
  "Charlton Brown Hobart|ホバート": "charlton-brown-hobart",
  "NIET Group Hobart|ホバート": "niet-group-hobart",
  "ELC Australian National University|キャンベラ": "elc-australian-national-university",
  "Britannia English Academy|マンチェスター": "britannia-english-academy",
  "Express English College Manchester|マンチェスター": "express-english-college-manchester",
  "English Path Leeds|リーズ": "english-path-leeds",
  "Kings Bournemouth|ボーンマス": "kings-bournemouth",
  "Bright School of English|ボーンマス": "bright-school-of-english",
  "Isca School of English|エクセター": "isca-school-of-english",
  "English in York|ヨーク": "english-in-york",
  "Languages United Bath|バース": "languages-united-bath",
  "BEST - Bath English Study Tours|バース": "best-bath-english-study-tours",
  "International House Bristol|ブリストル": "international-house-bristol",
  "Bristol Language Centre|ブリストル": "bristol-language-centre",
  "English in Margate|マーゲート": "english-in-margate",
  "Edinburgh School of English|エディンバラ": "edinburgh-school-of-english",
  "Oxford International Edinburgh|エディンバラ": "oxford-international-edinburgh",
  "St Andrew's College Glasgow|グラスゴー": "st-andrews-college-glasgow",
  "Apollo Language Centre|ダブリン": "apollo-language-centre",
  "Galway Language Centre|ゴールウェイ": "galway-language-centre",
  "Mackdonald Language Academy|キルケニー": "mackdonald-language-academy",
  "LCI Language School Vancouver|バンクーバー": "lci-language-school-vancouver",
  "LCI Language School Montreal|モントリオール": "lci-language-school-montreal",
  "Canada College School of Languages Montreal|モントリオール": "canada-college-school-of-languages-montreal",
  "International Gateway Kelowna|ケロウナ": "international-gateway-kelowna",
  "MacEwan University ESL Edmonton|エドモントン": "macewan-university-esl-edmonton",
  "NorQuest College ESL Edmonton|エドモントン": "norquest-college-esl-edmonton",
  "Berlitz Calgary|カルガリー": "berlitz-calgary",
  "Berlitz Edmonton|エドモントン": "berlitz-edmonton",
  "Berlitz Victoria|ビクトリア": "berlitz-victoria",
  "Berlitz Winnipeg|ウィニペグ": "berlitz-winnipeg",
  "Berlitz Ottawa|オタワ": "berlitz-ottawa",
  "TALK Schools USA|Multiple": "talk-schools-usa-multiple",
  "EF San Diego|サンディエゴ": "ef-san-diego",
  "Language On Miami|マイアミ": "language-on-miami",
  "MILA Academy Miami|マイアミ": "mila-academy-miami",
  "Language Consultants International Denver|デンバー": "language-consultants-international-denver",
  "Columbia School of English Portland|ポートランド": "columbia-school-of-english-portland",
  "A.C.E. Seattle Pacific University|シアトル": "ace-seattle-pacific-university",
  "North Shore Language School|オークランド": "north-shore-language-school",
  "Auckland English Academy|オークランド": "auckland-english-academy",
  "English Language Academy University of Auckland|オークランド": "english-language-academy-university-of-auckland",
  "The Campbell Institute Wellington|ウェリントン": "the-campbell-institute-wellington",
  "LSNZ Christchurch|クライストチャーチ": "lsnz-christchurch",
  "Impact English Brisbane|ブリスベン": "impact-english-brisbane",
  "Impact English Melbourne|メルボルン": "impact-english-melbourne",
  "Langports Sunshine Coast|Sunshine Coast": "langports-sunshine-coast-sunshine-coast",
  "Worcester School of English|Worcester": "worcester-school-of-english-worcester",
  "Stafford House Cambridge|Cambridge": "stafford-house-cambridge-cambridge",
  "St Giles Cambridge|Cambridge": "st-giles-cambridge-cambridge",
  "St Giles Brighton|Brighton": "st-giles-brighton-brighton",
  "St Giles Eastbourne|Eastbourne": "st-giles-eastbourne-eastbourne",
  "St Giles Highgate London|ロンドン": "st-giles-highgate-london",
  "Kings London|ロンドン": "kings-london",
  "Kings Oxford|Oxford": "kings-oxford-oxford",
  "Kings Cambridge|Cambridge": "kings-cambridge-cambridge",
  "Kings Hastings|ヘイスティングス": "kings-hastings",
  "UCEDA International USA|Multiple": "uceda-international-usa-multiple",
  "Midwestern Career College ESL Chicago|シカゴ": "midwestern-career-college-esl-chicago",
  "Kaplan International Washington DC|ワシントンDC": "kaplan-international-washington-dc-dc",
  "SSLC Vancouver|バンクーバー": "sslc-vancouver",
  "SSLC Toronto|トロント": "sslc-toronto",
  "Tamwood Language Centres Vancouver|バンクーバー": "tamwood-language-centres-vancouver",
  "Tamwood Language Centres Toronto|トロント": "tamwood-language-centres-toronto",
  "Delfin English School|ダブリン": "delfin-english-school",
  "Ability English Brisbane|ブリスベン": "ability-english-brisbane",
  "Ability English Gold Coast|ゴールドコースト": "ability-english-gold-coast",
  "Crown English College Brisbane|ブリスベン": "crown-english-college-brisbane",
  "RMIT University English Language Centre|メルボルン": "rmit-university-english-language-centre",
  "University of Sydney English Language Centre|シドニー": "university-of-sydney-english-language-centre",
  "Inhispania|グラナダ": "inhispania",
  "Estudio Sampere Madrid|マドリード": "estudio-sampere-madrid",
  "Carmen de las Cuevas|グラナダ": "carmen-de-las-cuevas",
  "Malaca Instituto|マラガ": "malaca-instituto",
  "Taronja|バレンシア": "taronja",
  "Tía Tula|サラマンカ": "tia-tula",
  "La Aventura Española (LAE Madrid)|マドリード": "la-aventura-espanola-lae-madrid",
  "Escuela de Idiomas Nerja|ネルハ": "escuela-de-idiomas-nerja",
  "Quorum Spanish Language School|ネルハ": "quorum-spanish-language-school",
  "Sevilla Habla|セビリア": "sevilla-habla",
  "Cervantes EI Seville|セビリア": "cervantes-ei-seville",
  "Hispanía Seville|セビリア": "hispania-seville",
  "CESA Languages Valencia|バレンシア": "cesa-languages-valencia",
  "AIP Language Institute Valencia|バレンシア": "aip-language-institute-valencia",
  "Route 66 Idiomas Valencia|バレンシア": "route-66-idiomas-valencia",
  "Españolé Valencia|バレンシア": "espanole-valencia",
  "Deutsche Akademie Hamburg|ハンブルク": "deutsche-akademie-hamburg",
  "Deutsche Akademie Frankfurt|フランクフルト": "deutsche-akademie-frankfurt",
  "Deutsche Akademie Cologne|ケルン": "deutsche-akademie-cologne",
  "TANDEM Cologne|ケルン": "tandem-cologne",
  "TANDEM Frankfurt|フランクフルト": "tandem-frankfurt",
  "Carl Duisberg Centrum Cologne|ケルン": "carl-duisberg-centrum-cologne",
  "Les Ateliers FL Paris|パリ": "les-ateliers-fl-paris",
  "Les Ateliers FL Nice|ニース": "les-ateliers-fl-nice",
  "Les Ateliers FL Lyon|リヨン": "les-ateliers-fl-lyon",
  "Les Ateliers FL Bordeaux|ボルドー": "les-ateliers-fl-bordeaux",
  "Les Ateliers FL Biarritz|ビアリッツ": "les-ateliers-fl-biarritz",
  "ILCF Lyon|リヨン": "ilcf-lyon",
  "ACCORD-PARIS|パリ": "accord-paris",
  "Centre International d'Antibes|Antibes": "centre-international-dantibes-antibes",
  "Accent Français Montpellier|モンペリエ": "accent-francais-montpellier",
  "Alliance Française Montpellier|モンペリエ": "alliance-francaise-montpellier",
  "ILA Montpellier|モンペリエ": "ila-montpellier",
  "LSF Montpellier|モンペリエ": "lsf-montpellier",
  "KLF Toulouse|トゥールーズ": "klf-toulouse",
  "Langue Onze Toulouse|トゥールーズ": "langue-onze-toulouse",
  "Alliance Française Marseille|マルセイユ": "alliance-francaise-marseille",
  "Alliance Française Aix-en-Provence|エクス=アン=プロヴァンス": "alliance-francaise-aix-en-provence",
  "Europass Italian Language School|フィレンツェ": "europass-italian-language-school",
  "Dante Alighieri Recanati|Recanati": "dante-alighieri-recanati-recanati",
  "Instituto Venezia Venice|ニース": "instituto-venezia-venice",
  "Istituto Venezia Trieste|トリエステ": "istituto-venezia-trieste",
  "QQ English|セブ": "qq-english",
  "Genius English Academy|セブ": "genius-english-academy",
  "English Fella|セブ": "english-fella",
  "Curious World Academy|セブ": "curious-world-academy",
  "HELP English Academy Clark|クラーク": "help-english-academy-clark",
  "JIC Academy|バギオ": "jic-academy",
  "WALES Academy|バギオ": "wales-academy",
  "WE ACADEMY Clark|クラーク": "we-academy-clark",
  "Alpha School of English|スリーマ": "alpha-school-of-english",
  "Clubclass English Language School|スリーマ": "clubclass-english-language-school",
  "Easy School of Languages|スリーマ": "easy-school-of-languages",
  "European School of English|スリーマ": "european-school-of-english",
  "Inlingua Malta|スリーマ": "inlingua-malta",
  "Institute of English Language Studies|スリーマ": "institute-of-english-language-studies",
  "LEXIS KOREA Busan|釜山": "lexis-korea-busan",
  "Seoul National University Korean Language Program|ソウル": "seoul-national-university-korean-language-program",
  "Kyunghee University Institute of International Education|ソウル": "kyunghee-university-institute-of-international-edu-2",
  "Sogang University Korean Language Program|ソウル": "sogang-university-korean-language-program",
  "Rolling Korea|ソウル": "rolling-korea",
  "Korean Language Institute For Foreigners (KLIFF)|釜山": "korean-language-institute-for-foreigners-kliff",
  "LTL Korea|ソウル": "ltl-korea",
  "ISI Tokyo|東京": "isi-tokyo",
  "ISI Kyoto|京都": "isi-kyoto",
  "ISI Osaka|大阪": "isi-osaka",
  "Genki Japanese and Culture School Tokyo|東京": "genki-japanese-and-culture-school-tokyo-2",
  "Genki Japanese and Culture School Kyoto|京都": "genki-japanese-and-culture-school-kyoto",
  "Kyoshin Japanese Language School Tokyo|東京": "kyoshin-japanese-language-school-tokyo",
  "Kyoshin Japanese Language School Osaka|大阪": "kyoshin-japanese-language-school-osaka",
  "Kyoshin Japanese Language School Kyoto|京都": "kyoshin-japanese-language-school-kyoto",
  "TSL Chiang Mai|チェンマイ": "tsl-chiang-mai",
  "Lanna Language|チェンマイ": "lanna-language",
  "Payap University Intensive Thai Program|チェンマイ": "payap-university-intensive-thai-program-2",
  "Pro Language School Bangkok|バンコク": "pro-language-school-bangkok",
  "Pro Language School Chiang Mai|チェンマイ": "pro-language-school-chiang-mai",
  "Manna Thai Language|バンコク": "manna-thai-language",
  "Thai Language Hut|バンコク": "thai-language-hut",
  "Agora Language Center|プラヤ・デル・カルメン": "agora-language-center",
  "Don Quijote Playa del Carmen|プラヤ・デル・カルメン": "don-quijote-playa-del-carmen",
  "Viva Idioma|プラヤ・デル・カルメン": "viva-idioma",
  "Tann Spanish School|プラヤ・デル・カルメン": "tann-spanish-school",
  "Chichén Itzá Language School|プラヤ・デル・カルメン": "chichen-itza-language-school",
  "International House Riviera Maya|プラヤ・デル・カルメン": "international-house-riviera-maya",
  "Alegre Spanish Schools Playa del Carmen|プラヤ・デル・カルメン": "alegre-spanish-schools-playa-del-carmen",
  "Instituto Cultural Oaxaca|オアハカ": "instituto-cultural-oaxaca",
  "Oaxaca International|オアハカ": "oaxaca-international",
  "La Guarida Spanish School|オアハカ": "la-guarida-spanish-school",
  "Oaxaca Spanish Magic|オアハカ": "oaxaca-spanish-magic",
  "Spanish School Guadalajara|グアダラハラ": "spanish-school-guadalajara",
  "Total Spanish Medellin|メデジン": "total-spanish-medellin",
  "Total Spanish Cartagena|カルタヘナ": "total-spanish-cartagena",
  "Centro Catalina Cartagena|カルタヘナ": "centro-catalina-cartagena",
  "Centro Catalina Medellin|メデジン": "centro-catalina-medellin",
  "Valley Spanish School Medellin|メデジン": "valley-spanish-school-medellin",
  "Valley Spanish School Cartagena|カルタヘナ": "valley-spanish-school-cartagena",
  "Valley Spanish School Bogota|ボゴタ": "valley-spanish-school-bogota",
  "Toucan Spanish Medellin|メデジン": "toucan-spanish-medellin",
  "Toucan Spanish Cali|カリ": "toucan-spanish-cali",
  "Vamos Academy Colombia Medellin|メデジン": "vamos-academy-colombia-medellin",
  "Vamos Academy Colombia Cartagena|カルタヘナ": "vamos-academy-colombia-cartagena",
  "Ailola Buenos Aires|ブエノスアイレス": "ailola-buenos-aires",
  "Vamos Academy Argentina|ブエノスアイレス": "vamos-academy-argentina",
  "Mente Argentina|ブエノスアイレス": "mente-argentina",
  "Academia Buenos Aires|ブエノスアイレス": "academia-buenos-aires",
  "Ibero Spanish School|ブエノスアイレス": "ibero-spanish-school",
  "Elebaires|ブエノスアイレス": "elebaires",
  "Maximo Nivel Manuel Antonio|Manuel Antonio": "maximo-nivel-manuel-antonio-manuel-antonio",
  "Manuel Antonio Spanish School|Manuel Antonio": "manuel-antonio-spanish-school-manuel-antonio",
  "Academia Tica|San Jose": "academia-tica-san-jose",
  "AMAUTA Spanish School Lima|リマ": "amauta-spanish-school-lima",
  "Llama Education|Arequipa": "llama-education-arequipa",
  "Ceica Peru|Arequipa": "ceica-peru-arequipa",
  "CEPESMA Idiomas|Arequipa": "cepesma-idiomas-arequipa",
  "Instituto Superior de Español Quito|キト": "instituto-superior-de-espanol-quito",
  "Instituto Superior de Español Otavalo|Otavalo": "instituto-superior-de-espanol-otavalo-otavalo",
  "Pucara Spanish School|Cotacachi": "pucara-spanish-school-cotacachi",
  "OLA Spanish School Otavalo|Otavalo": "ola-spanish-school-otavalo-otavalo",
  "Escuela Bellavista Santiago|サンティアゴ": "escuela-bellavista-santiago",
  "Natalislang Santiago|サンティアゴ": "natalislang-santiago",
  "Cultura Inglesa Rio|リオデジャネイロ": "cultura-inglesa-rio",
  "Cultura Inglesa Sao Paulo|サンパウロ": "cultura-inglesa-sao-paulo",
  "Cultura Inglesa Brasilia|Brasilia": "cultura-inglesa-brasilia-brasilia",
  "Cultura Inglesa Recife|Recife": "cultura-inglesa-recife-recife",
  "CNA Brazil|サンパウロ": "cna-brazil",
  "Portuguese Connection Language School|リスボン": "portuguese-connection-language-school",
  "Lighthouse Language School Lisbon|リスボン": "lighthouse-language-school-lisbon",
  "CIAL Porto|ポルト": "cial-porto",
  "Swiss French School Geneva|ジュネーブ": "swiss-french-school-geneva",
  "Learn French Geneva - Swiss Language Academy|ジュネーブ": "learn-french-geneva-swiss-language-academy",
  "Alliance Française de Zurich|チューリッヒ": "alliance-francaise-de-zurich",
  "LSI Montreux|モントルー": "lsi-montreux",
  "Nedles Amsterdam|アムステルダム": "nedles-amsterdam",
  "Koentact Amsterdam|アムステルダム": "koentact-amsterdam",
  "The School for Dutch Amsterdam|アムステルダム": "the-school-for-dutch-amsterdam",
  "Language Corner Amsterdam|アムステルダム": "language-corner-amsterdam",
  "TaalBoost Amsterdam|アムステルダム": "taalboost-amsterdam",
  "British Council Penang|ペナン": "british-council-penang",
  "ELS Malaysia Kuala Lumpur|クアラルンプール": "els-malaysia-kuala-lumpur",
  "EMS Language Center|クアラルンプール": "ems-language-center",
  "ELEC Centre Kuala Lumpur|クアラルンプール": "elec-centre-kuala-lumpur",
  "Canadian Education College Singapore|シンガポール": "canadian-education-college-singapore",
  "School of Language International Singapore|シンガポール": "school-of-language-international-singapore",
  "ULC Singapore|シンガポール": "ulc-singapore",
  "EF International Language Center Singapore|シンガポール": "ef-international-language-center-singapore",
  "EC Dubai|ドバイ": "ec-dubai",
  "English Path Dubai|ドバイ": "english-path-dubai",
  "British Council Delhi|ニューデリー": "british-council-delhi",
  "Stanford English Academy Mumbai|ムンバイ": "stanford-english-academy-mumbai",
  "Cairns College of English and Business|ケアンズ": "cairns-college-of-english-and-business",
  "Holmes Institute Cairns|ケアンズ": "holmes-institute-cairns",
  "Flinders University Academy|アデレード": "flinders-university-academy",
  "SACE Tasmanian College of English|ホバート": "sace-tasmanian-college-of-english",
  "Canberra Institute of Technology|キャンベラ": "canberra-institute-of-technology",
  "Abbey College Townsville|Townsville": "abbey-college-townsville-townsville",
  "Apollo English Fremantle|パース": "apollo-english-fremantle",
  "English for Success Adelaide|アデレード": "english-for-success-adelaide",
  "Macquarie University Centre for English Language|シドニー": "macquarie-university-centre-for-english-language",
  "University of New England ELICOS|Armidale": "university-of-new-england-elicos-armidale",
  "RMIT English Worldwide|メルボルン": "rmit-english-worldwide",
  "UTS Insearch English|シドニー": "uts-insearch-english",
  "Murdoch University English Language Centre|パース": "murdoch-university-english-language-centre",
  "Australian Catholic University English|キャンベラ": "australian-catholic-university-english",
  "Sunnybank English Language Institute|ブリスベン": "sunnybank-english-language-institute",
  "Academies Australasia|シドニー": "academies-australasia",
  "Greenwich English College|シドニー": "greenwich-english-college",
  "Australian Institute of English|メルボルン": "australian-institute-of-english",
  "Oxford English Academy|オックスフォード": "oxford-english-academy",
  "Cambridge English School|ケンブリッジ": "cambridge-english-school",
  "Brighton Language School|ブライトン": "brighton-language-school",
  "Bournemouth English Academy|ボーンマス": "bournemouth-english-academy",
  "Southampton English School|Southampton": "southampton-english-school-southampton",
  "Norwich School of English|ノリッジ": "norwich-school-of-english",
  "York English School|ヨーク": "york-english-school",
  "Manchester English Academy|マンチェスター": "manchester-english-academy",
  "Edinburgh International School|エディンバラ": "edinburgh-international-school",
  "Liverpool Language School|リバプール": "liverpool-language-school",
  "Torquay English Academy|トーキー": "torquay-english-academy",
  "Bath English Academy|バース": "bath-english-academy",
  "Columbia University American Language Program|ヨーク": "columbia-university-american-language-program",
  "University of Pennsylvania English Language Program|フィラデルフィア": "university-of-pennsylvania-english-language-progra",
  "Florida Atlantic University Intensive English Institute|Boca Raton": "florida-atlantic-university-intensive-english-inst",
  "Harvest English Institute Los Angeles|ロサンゼルス": "harvest-english-institute-los-angeles",
  "Harvest English Institute Orlando|Orlando": "harvest-english-institute-orlando-orlando",
  "American Language Institute Boston|ボストン": "american-language-institute-boston",
  "Seattle English Academy|シアトル": "seattle-english-academy",
  "Austin English Program|Austin": "austin-english-program-austin",
  "San Francisco English Academy|サンフランシスコ": "san-francisco-english-academy",
  "Denver English Institute|デンバー": "denver-english-institute",
  "Chicago English Academy|シカゴ": "chicago-english-academy",
  "Washington English Academy|Washington": "washington-english-academy-washington",
  "Miami English Academy|マイアミ": "miami-english-academy",
  "ILSC Canada Vancouver|バンクーバー": "ilsc-canada-vancouver",
  "ILSC Canada Toronto|トロント": "ilsc-canada-toronto",
  "Global Village Toronto|トロント": "global-village-toronto",
  "Oxford House College Vancouver|バンクーバー": "oxford-house-college-vancouver",
  "Cornerstone English Academy Calgary|カルガリー": "cornerstone-english-academy-calgary",
  "Kaplan International Canada Toronto|トロント": "kaplan-international-canada-toronto",
  "Eurocentres Canada Vancouver|バンクーバー": "eurocentres-canada-vancouver",
  "QQ English Seagarden Campus|セブ": "qq-english-seagarden-campus",
  "Philinter Education Center|セブ": "philinter-education-center",
  "CWA English Academy|セブ": "cwa-english-academy",
  "ABC English School|セブ": "abc-english-school",
  "CET Cebu ESL Academy|セブ": "cet-cebu-esl-academy",
  "Cebu Languages Academy|セブ": "cebu-languages-academy",
  "JForrest English Academy|バギオ": "jforrest-english-academy",
  "Pines Academy Baguio|バギオ": "pines-academy-baguio",
  "TALK English Schools Baguio|バギオ": "talk-english-schools-baguio",
  "Sunburst English Academy Cebu|セブ": "sunburst-english-academy-cebu",
  "Perfect English Academy Baguio|バギオ": "perfect-english-academy-baguio",
  "Spanish in Cadiz|カディス": "spanish-in-cadiz",
  "Instituto Hemingway Bilbao|Bilbao": "instituto-hemingway-bilbao-bilbao",
  "ID Nerja Spanish School|ネルハ": "id-nerja-spanish-school",
  "CLIC International House Cadiz|カディス": "clic-international-house-cadiz",
  "K2 Internacional Cadiz|カディス": "k2-internacional-cadiz",
  "Don Quijote Tarragona|Tarragona": "don-quijote-tarragona-tarragona",
  "Estudio Hispanico Girona|Girona": "estudio-hispanico-girona-girona",
  "UFORIC Palmas Gran Canaria|Las Palmas": "uforic-palmas-gran-canaria-las-palmas",
  "Pamplona Spanish School|Pamplona": "pamplona-spanish-school-pamplona",
  "Konstanz Language School|Konstanz": "konstanz-language-school-konstanz",
  "Horizonte Regensburg|Regensburg": "horizonte-regensburg-regensburg",
  "Evolanguage Aachen|Aachen": "evolanguage-aachen-aachen",
  "Wiesbaden Language Centre|Wiesbaden": "wiesbaden-language-centre-wiesbaden",
  "Mannheim Language Institute|Mannheim": "mannheim-language-institute-mannheim",
  "Horizonte Cannes|Cannes": "horizonte-cannes-cannes",
  "Ecole de Langue Vichy|Vichy": "ecole-de-langue-vichy-vichy",
  "Institut de Français Tours|Tours": "institut-de-francais-tours-tours",
  "Annecy French Academy|Annecy": "annecy-french-academy-annecy",
  "La Rochelle Language School|La Rochelle": "la-rochelle-language-school-la-rochelle",
  "Institut de Nancy|Nancy": "institut-de-nancy-nancy",
  "Comitato Linguistico Perugia|Perugia": "comitato-linguistico-perugia-perugia",
  "Scuola Leonardo da Vinci Verona|Verona": "scuola-leonardo-da-vinci-verona-verona",
  "Scuola Leonardo da Vinci Turin|Turin": "scuola-leonardo-da-vinci-turin-turin",
  "Porta d'Oriente Perugia|Perugia": "porta-doriente-perugia-perugia",
  "Italian Language Institute Palermo|Palermo": "italian-language-institute-palermo-palermo",
  "The Umbra Institute Perugia|Perugia": "the-umbra-institute-perugia-perugia",
  "am Language|スリーマ": "am-language",
  "Clubclass English School|Gzira": "clubclass-english-school-gzira",
  "Portugal Linguística|リスボン": "portugal-linguistica",
  "Portuguese Language Institute|ポルト": "portuguese-language-institute",
  "Fado Portuguese School|リスボン": "fado-portuguese-school",
  "Wuhan University International Student Office|武漢": "wuhan-university-international-student-office",
  "Sichuan University Chinese Program|成都": "sichuan-university-chinese-program",
  "Nanjing University Chinese Language Centre|南京": "nanjing-university-chinese-language-centre",
  "Xi'an Jiaotong University|西安": "xian-jiaotong-university-2",
  "Harbin Institute of Technology|Harbin": "harbin-institute-of-technology-harbin",
  "Dalian University of Technology|大連": "dalian-university-of-technology",
  "Qingdao University|青島": "qingdao-university",
  "Xiamen University|廈門": "xiamen-university-2",
  "Meiji Academy Hokkaido|札幌": "meiji-academy-hokkaido",
  "JaLS GROUP Tokyo|東京": "jals-group-tokyo",
  "ARC Academy Osaka|大阪": "arc-academy-osaka",
  "Genki Japanese School Kyoto|京都": "genki-japanese-school-kyoto",
  "Fukuoka Language Institute|福岡": "fukuoka-language-institute",
  "Nagoya Japanese Language School|名古屋": "nagoya-japanese-language-school",
  "Seoul National University Korean Language Center|ソウル": "seoul-national-university-korean-language-center",
  "Yonsei University Korean Language Institute|ソウル": "yonsei-university-korean-language-institute",
  "Green Korean Language School|ソウル": "green-korean-language-school",
  "Ganada Korean Language Institute|ソウル": "ganada-korean-language-institute",
  "Ewha Womans University Korean Language Center|ソウル": "ewha-womans-university-korean-language-center",
  "IH Bangkok|バンコク": "ih-bangkok",
  "AUA Language Center Bangkok|バンコク": "aua-language-center-bangkok",
  "IH Chiang Mai|チェンマイ": "ih-chiang-mai",
  "MDIS School of Languages|シンガポール": "mdis-school-of-languages",
  "ELS Language Centre Kuala Lumpur|クアラルンプール": "els-language-centre-kuala-lumpur",
  "ALC Language School Kuala Lumpur|クアラルンプール": "alc-language-school-kuala-lumpur",
  "IMAC Spanish Language Programs|Cuernavaca": "imac-spanish-language-programs-cuernavaca",
  "Lengua y Cultura Spanish School|メキシコシティ": "lengua-y-cultura-spanish-school",
  "WalkSpanish Mexico City|メキシコシティ": "walkspanish-mexico-city",
  "Puerto School Playa del Carmen|プラヤ・デル・カルメン": "puerto-school-playa-del-carmen",
  "SIP Puebla|Puebla": "sip-puebla-puebla",
  "OLSA International Medellin|メデジン": "olsa-international-medellin",
  "Total Spanish Colombia|メデジン": "total-spanish-colombia",
  "Toucan Spanish Bogota|ボゴタ": "toucan-spanish-bogota",
  "SWI Spanish School Bogota|ボゴタ": "swi-spanish-school-bogota",
  "Don Quijote Lima|リマ": "don-quijote-lima",
  "LatinoSchools Cusco|クスコ": "latinoschools-cusco",
  "Estudio Hispanico Peru|リマ": "estudio-hispanico-peru",
  "Don Quijote Quito|キト": "don-quijote-quito",
  "LatinoSchools Quito|キト": "latinoschools-quito",
  "Estudio Hispanico Ecuador|キト": "estudio-hispanico-ecuador",
  "Intercoined Ecuador|キト": "intercoined-ecuador",
  "Don Quijote San Jose|San José": "don-quijote-san-jose-san-jose",
  "Estudio Hispanico Costa Rica|San José": "estudio-hispanico-costa-rica-san-jose",
  "Don Quijote Antigua|アンティグア": "don-quijote-antigua",
  "Estudio Hispanico Guatemala|Guatemala City": "estudio-hispanico-guatemala-guatemala-city",
  "Maximo Nivel Guatemala|アンティグア": "maximo-nivel-guatemala",
  "Don Quijote Santiago|サンティアゴ": "don-quijote-santiago",
  "Estudio Hispanico Chile|サンティアゴ": "estudio-hispanico-chile",
  "Intercoined Chile|サンティアゴ": "intercoined-chile",
  "Taipei Language Institute|台北": "taipei-language-institute",
  "Taiwan Mandarin Institute|台北": "taiwan-mandarin-institute",
  "ShuoHao Language Center Taipei|台北": "shuohao-language-center-taipei",
  "LTL Language School Taiwan|台北": "ltl-language-school-taiwan",
  "Taiwan Chinese Academy|台北": "taiwan-chinese-academy",
  "ShuoHao Language Center Taichung|台中": "shuohao-language-center-taichung",
  "National Taiwan University Mandarin Training Center|台北": "national-taiwan-university-mandarin-training-cente",
  "National Taiwan Normal University Mandarin Center|台北": "national-taiwan-normal-university-mandarin-center",
  "LTL Language School Hanoi|ハノイ": "ltl-language-school-hanoi",
  "LTL Language School Ho Chi Minh|ホーチミン": "ltl-language-school-ho-chi-minh",
  "123Vietnamese Hanoi|ハノイ": "123vietnamese-hanoi",
  "123Vietnamese Ho Chi Minh|ホーチミン": "123vietnamese-ho-chi-minh",
  "Vietnamese Language Garden|ホーチミン": "vietnamese-language-garden",
  "Saigon Language School|ホーチミン": "saigon-language-school",
  "Vietnam National University Language Center|ハノイ": "vietnam-national-university-language-center",
  "123Vietnamese Da Nang|Da Nang": "123vietnamese-da-nang-da-nang",
  "STAR Exeter|エクセター": "star-exeter",
  "Cambridge Academy of English|ケンブリッジ": "cambridge-academy-of-english",
  "Colchester English Centre|Colchester": "colchester-english-centre-colchester",
  "Hastings English School|Hastings": "hastings-english-school-hastings",
  "Plymouth English Academy|Plymouth": "plymouth-english-academy-plymouth",
  "Worcester English School|Worcester": "worcester-english-school-worcester",
  "Coventry English Academy|Coventry": "coventry-english-academy-coventry",
  "Leicester English School|Leicester": "leicester-english-school-leicester",
  "Leeds English Academy|リーズ": "leeds-english-academy",
  "EC English Boston|ボストン": "ec-english-boston",
  "EC English San Diego|サンディエゴ": "ec-english-san-diego",
  "EC English San Francisco|サンフランシスコ": "ec-english-san-francisco",
  "LCI Denver|デンバー": "lci-denver",
  "EC English Denver|デンバー": "ec-english-denver",
  "EC English New York|ヨーク": "ec-english-new-york",
  "EC English Los Angeles|ロサンゼルス": "ec-english-los-angeles",
  "TALK Schools Boston|ボストン": "talk-schools-boston",
  "Nacel Boston|ボストン": "nacel-boston",
  "Nacel San Diego|サンディエゴ": "nacel-san-diego",
  "Nacel San Francisco|サンフランシスコ": "nacel-san-francisco",
  "Navitas English Sydney additional|シドニー": "navitas-english-sydney-additional",
  "ELS Adelaide|アデレード": "els-adelaide",
  "Kaplan Melbourne additional|メルボルン": "kaplan-melbourne-additional",
  "EC English Sydney|シドニー": "ec-english-sydney",
  "EC English Melbourne|メルボルン": "ec-english-melbourne",
  "EF English Sydney|シドニー": "ef-english-sydney",
  "EF English Melbourne|メルボルン": "ef-english-melbourne",
  "EF English Brisbane|ブリスベン": "ef-english-brisbane",
  "EF English Vancouver|バンクーバー": "ef-english-vancouver",
  "EF English Toronto|トロント": "ef-english-toronto",
  "EC English Toronto|トロント": "ec-english-toronto",
  "Kaplan International Canada Vancouver additional|バンクーバー": "kaplan-international-canada-vancouver-additional",
  "Tamwood College Vancouver|バンクーバー": "tamwood-college-vancouver",
  "Tamwood College Toronto|トロント": "tamwood-college-toronto",
  "Inlingua Toronto|トロント": "inlingua-toronto",
  "CLIC Seville|セビリア": "clic-seville",
  "Instituto Hemingway Cordoba|Córdoba": "instituto-hemingway-cordoba-cordoba",
  "Estudio Hispanico Barcelona|バルセロナ": "estudio-hispanico-barcelona",
  "CLIC Barcelona|バルセロナ": "clic-barcelona",
  "Estudio Hispanico France Paris|パリ": "estudio-hispanico-france-paris",
  "ILC France Montpellier|モンペリエ": "ilc-france-montpellier",
  "AILC Lyon|リヨン": "ailc-lyon",
  "Provence Language School Aix-en-Provence|Aix-en-Provence": "provence-language-school-aix-en-provence-aix-en-pr",
  "Accademia Italiana Florence|フィレンツェ": "accademia-italiana-florence",
  "Dante Alighieri Rome|ローマ": "dante-alighieri-rome",
  "Sprachschule Aktiv Berlin|ベルリン": "sprachschule-aktiv-berlin",
  "Sprachschule Aktiv Munich|ミュンヘン": "sprachschule-aktiv-munich",
  "Sprachzentrum Dresden|Dresden": "sprachzentrum-dresden-dresden",
  "Inlingua Hamburg|ハンブルク": "inlingua-hamburg",
  "Meiji Academy Tokyo|東京": "meiji-academy-tokyo",
  "Meiji Academy Osaka|大阪": "meiji-academy-osaka",
  "AIEJ Tokyo|東京": "aiej-tokyo",
  "ISI Japanese Language School Tokyo|東京": "isi-japanese-language-school-tokyo",
  "Genki Japanese School Fukuoka|福岡": "genki-japanese-school-fukuoka",
  "Miyako Japanese Academy Tokyo|東京": "miyako-japanese-academy-tokyo",
  "Sogang University Korean Language Center|ソウル": "sogang-university-korean-language-center",
  "Korea University Korean Language Center|ソウル": "korea-university-korean-language-center",
  "Hanyang University Korean Language Institute|ソウル": "hanyang-university-korean-language-institute",
  "Dongguk University Korean Language Institute|ソウル": "dongguk-university-korean-language-institute",
  "Kyunghee University Korean Language Institute|ソウル": "kyunghee-university-korean-language-institute",
  "Zhejiang University|杭州": "zhejiang-university-2",
  "Huazhong University of Science and Technology|武漢": "huazhong-university-of-science-and-technology-2",
  "Tianjin University|天津": "tianjin-university-2",
  "Wuhan Linguistics University|武漢": "wuhan-linguistics-university",
  "Shandong University Jinan|Jinan": "shandong-university-jinan-jinan",
  "EV English Academy Cebu|セブ": "ev-english-academy-cebu",
  "Genius English Proficiency Institute Cebu|セブ": "genius-english-proficiency-institute-cebu",
  "Geniusenglish Baguio|バギオ": "geniusenglish-baguio",
  "HELP English Course Cebu|セブ": "help-english-course-cebu",
  "HELP English Course Baguio|バギオ": "help-english-course-baguio",
  "C2 Ubec English Academy Cebu|セブ": "c2-ubec-english-academy-cebu",
  "Bayside International Academy Baguio|バギオ": "bayside-international-academy-baguio",
  "WEP English Academy Cebu|セブ": "wep-english-academy-cebu",
  "Don Quijote Panama|Panama City": "don-quijote-panama-panama-city",
  "Linguadona Dominican Republic|Santo Domingo": "linguadona-dominican-republic-santo-domingo",
  "Intercoined Guatemala|アンティグア": "intercoined-guatemala",
  "Don Quijote El Salvador|San Salvador": "don-quijote-el-salvador-san-salvador",
  "ILISA Madrid|マドリード": "ilisa-madrid",
  "ILISA Barcelona|バルセロナ": "ilisa-barcelona",
  "British Council Dubai|ドバイ": "british-council-dubai",
  "IH Bangkok Sukhumvit|バンコク": "ih-bangkok-sukhumvit",
  "AUA Bangkok Sathorn|バンコク": "aua-bangkok-sathorn",
  "EF English Kuala Lumpur|クアラルンプール": "ef-english-kuala-lumpur",
  "Cavendish School of English London|ロンドン": "cavendish-school-of-english-london",
  "Berlitz London|ロンドン": "berlitz-london",
  "CLIC IH Dublin|ダブリン": "clic-ih-dublin",
  "LSI Dublin|ダブリン": "lsi-dublin",
  "Sprachschule Aktiv Vienna|ウィーン": "sprachschule-aktiv-vienna",
  "International House Vienna|ウィーン": "international-house-vienna",
  "Inlingua Prague|プラハ": "inlingua-prague",
  "Berlitz Prague|プラハ": "berlitz-prague",
  "Inlingua Budapest|Budapest": "inlingua-budapest-budapest",
  "EC Zurich|チューリッヒ": "ec-zurich",
  "Kaplan International Canada Calgary|カルガリー": "kaplan-international-canada-calgary",
  "EF English Montréal|Montréal": "ef-english-montreal-montreal",
  "EC English Montréal|Montréal": "ec-english-montreal-montreal",
  "Sprachschule Aktiv Stuttgart|Stuttgart": "sprachschule-aktiv-stuttgart-stuttgart",
  "Inlingua Stuttgart|Stuttgart": "inlingua-stuttgart-stuttgart",
  "Linguaschools Madrid|マドリード": "linguaschools-madrid",
  "Linguaschools Barcelona|バルセロナ": "linguaschools-barcelona",
  "Accademia Italiana Rome|ローマ": "accademia-italiana-rome",
  "Alpadia Language Schools Rome|ローマ": "alpadia-language-schools-rome",
  "EC Paris|パリ": "ec-paris",
  "Berlitz Paris|パリ": "berlitz-paris",
  "EF English Perth|パース": "ef-english-perth",
  "EC English Brisbane|ブリスベン": "ec-english-brisbane",
  "Opals English Sydney|シドニー": "opals-english-sydney",
  "Nova English Brisbane|ブリスベン": "nova-english-brisbane",
  "Imagine Education Australia Sydney|シドニー": "imagine-education-australia-sydney"
}
